vortexfitting/__init__.py
vortexfitting/__main__.py
vortexfitting/classes.py
vortexfitting/convertToASCII.py
vortexfitting/convertToNC.py
vortexfitting/detection.py
vortexfitting/fitting.py
vortexfitting/generateNetCDF.py
vortexfitting/output.py
vortexfitting/schemes.py
vortexfitting-1.0.1.dist-info/LICENSE
vortexfitting-1.0.1.dist-info/METADATA
vortexfitting-1.0.1.dist-info/WHEEL
vortexfitting-1.0.1.dist-info/entry_points.txt
vortexfitting-1.0.1.dist-info/top_level.txt
vortexfitting-1.0.1.dist-info/RECORD
