Metadata-Version: 2.1
Name: vortexfitting
Version: 1.0.1
Summary: A tool to locate and characterize vortices
Home-page: https://github.com/guilindner/VortexFitting
Author: Guilherme Anrain Lindner
Author-email: lindner.guilherme@gmail.com
License: MIT
Project-URL: Source, https://github.com/guilindner/VortexFitting
Keywords: vortex cfd fluid mechanics
Platform: UNKNOWN
Classifier: License :: OSI Approved :: MIT License
Classifier: Programming Language :: Python :: 3.6
Classifier: Programming Language :: Python :: 3.7
Classifier: Programming Language :: Python :: 3.8
Requires-Dist: netcdf4
Requires-Dist: matplotlib
Requires-Dist: numpy
Requires-Dist: scipy
